LvAut/__init__.py
LvAut/_cffi_backend.cp36-win32.pyd
LvAut/_cffi_backend.cp39-win32.pyd
LvAut/_cffi_backend.pyd
LvAut/_portaudio.cp36-win32.pyd
LvAut/_soundfile.py
LvAut/device.py
LvAut/lvaut_THD.cp36-win32.pyd
LvAut/lvaut_THD.cp39-win32.pyd
LvAut/lvaut_THD.pyd
LvAut/lvdisplay.py
LvAut/lvspectrum.py
LvAut/portaudio.dll
LvAut/six.py
LvAut/sound_level.py
LvAut/soundload.cp39-win32.pyd
LvAut/soundload.pyd
LvAut/time_frequency.py
LvAut/volume.dll
LvAut/__pycache__/__init__.cpython-36.pyc
LvAut/_soundfile_data/COPYING
LvAut/_soundfile_data/libsndfile32bit.dll
LvAut-2021.2.1.dist-info/METADATA
LvAut-2021.2.1.dist-info/WHEEL
LvAut-2021.2.1.dist-info/top_level.txt
LvAut-2021.2.1.dist-info/RECORD
