Metadata-Version: 2.1
Name: LvAut
Version: 2021.2.1
Summary: Audio sound file testing/analyzes module
Home-page: https://github.com/Lorrytoolcenter/LvAut
Author: lorry_rui
Author-email: lrui@logitech.com
License: UNKNOWN
Platform: UNKNOWN
Classifier: Programming Language :: Python :: 3
Classifier: License :: OSI Approved :: MIT License
Classifier: Operating System :: OS Independent
Requires-Python: >=3.6
